{
  "data": [
    {
      "country": "Canada",
      "artist_name": "ECHELON (International)",
      "currency": "EUR",
      "amount_paid_fmt": "€0.50",
      "item_price": 0,
      "slug_type": "a",
      "item_description": "The Brimstone Aggrandizement (Death Metal Supergroup)",
      "amount_paid": 0.5,
      "art_id": 2180639655,
      "art_url": "https://f4.bcbits.com/img/a2180639655_7.jpg",
      "amount_paid_usd": 0.53,
      "url": "https://echelondm.bandcamp.com/album/the-brimstone-aggrandizement-death-metal-supergroup",
      "item_type": "a",
      "country_code": "ca",
      "utc_date": 1654125263.78403,
      "details": {
        "type": "track",
        "stories": [
          "",
          "",
          "",
          "",
          "",
          "",
          "",
          "",
          "",
          "",
          "",
          "",
          "",
          "",
          "",
          "",
          ""
        ]
      }
    },
    {
      "utc_date": 1653877354.29856,
      "country": "Canada",
      "artist_name": "Echo Canyon",
      "currency": "CAD",
      "amount_paid_fmt": "$10 CAD",
      "item_price": 0,
      "slug_type": "a",
      "amount_paid": 10,
      "art_id": 2863941408,
      "url": "https://echocanyonband.bandcamp.com/album/the-lily-pad-demo-2",
      "country_code": "ca",
      "amount_over_fmt": "$10",
      "art_url": "https://f4.bcbits.com/img/a2863941408_7.jpg",
      "item_type": "a",
      "amount_paid_usd": 7.86,
      "item_description": "The Lily Pad Demo",
      "details": {
        "type": "album",
        "stories": [
          "",
          "",
          "",
          "",
          "",
          ""
        ]
      }
    },
    {
      "item_type": "a",
      "country_code": "ca",
      "utc_date": 1654311377.2838,
      "item_description": "Quand je l'ai regardé, je l'ai vu apparaître (en une seule longue piste)",
      "country": "Canada",
      "artist_name": "Écho vide",
      "currency": "CAD",
      "amount_paid_fmt": "$1 CAD",
      "item_price": 0,
      "slug_type": "a",
      "amount_paid": 1,
      "url": "https://echovide.bandcamp.com/album/quand-je-lai-regard-je-lai-vu-appara-tre-en-une-seule-longue-piste",
      "art_id": 798018237,
      "art_url": "https://f4.bcbits.com/img/a0798018237_7.jpg",
      "amount_paid_usd": 0.79,
      "details": {
        "type": "album",
        "stories": [
          "",
          "",
          "",
          "",
          ""
        ]
      }
    },
    {
      "item_type": "a",
      "country_code": "gr",
      "utc_date": 1654461142.81966,
      "country": "Greece",
      "artist_name": "Echolaliac",
      "currency": "USD",
      "amount_paid_fmt": "$1",
      "item_price": 0,
      "slug_type": "a",
      "amount_paid": 1,
      "url": "https://echolaliac.bandcamp.com/album/saya-no-uta",
      "art_id": 3533263101,
      "art_url": "https://f4.bcbits.com/img/a3533263101_7.jpg",
      "amount_paid_usd": 1,
      "item_description": "Saya no Uta",
      "details": {
        "type": "album",
        "stories": [
          "",
          "",
          "",
          "",
          ""
        ]
      }
    },
    {
      "utc_date": 1653702059.02656,
      "country": "United States",
      "item_description": "Candle Cove",
      "artist_name": "Echopraxia",
      "currency": "USD",
      "amount_paid_fmt": "$1",
      "item_price": 0,
      "slug_type": "a",
      "amount_paid": 1,
      "art_id": 399436499,
      "url": "https://echopraxia.bandcamp.com/album/candle-cove",
      "country_code": "us",
      "art_url": "https://f4.bcbits.com/img/a0399436499_7.jpg",
      "item_type": "a",
      "amount_paid_usd": 1,
      "details": {
        "type": "album",
        "stories": [
          "",
          "",
          "",
          "",
          ""
        ]
      }
    },
    {
      "item_description": "Phantasms of the Eclipse",
      "country": "United States",
      "artist_name": "ECLIPSE Sound Team",
      "currency": "USD",
      "amount_paid_fmt": "$5",
      "item_price": 0,
      "slug_type": "a",
      "amount_paid": 5,
      "art_id": 478280197,
      "amount_over_fmt": "$5",
      "art_url": "https://f4.bcbits.com/img/a0478280197_7.jpg",
      "amount_paid_usd": 5,
      "url": "https://eclipsesoundteam.bandcamp.com/album/phantasms-of-the-eclipse",
      "item_type": "a",
      "country_code": "us",
      "utc_date": 1654185444.87747,
      "details": {
        "type": "album",
        "stories": [
          "",
          "",
          "",
          "",
          "",
          "",
          "",
          "",
          "",
          ""
        ]
      }
    },
    {
      "country": "United States",
      "artist_name": "EclipticSelftet",
      "currency": "EUR",
      "amount_paid_fmt": "€0.50",
      "item_price": 0,
      "slug_type": "a",
      "amount_paid": 0.5,
      "item_description": "Ecliptic Collection #1",
      "art_id": 1970580108,
      "art_url": "https://f4.bcbits.com/img/a1970580108_7.jpg",
      "amount_paid_usd": 0.53,
      "url": "https://eclipticjesus.bandcamp.com/album/ecliptic-collection-1",
      "item_type": "a",
      "country_code": "us",
      "utc_date": 1654123556.40028,
      "details": {
        "type": "album",
        "stories": [
          "",
          "",
          "",
          "",
          "",
          "",
          "",
          "",
          "",
          "",
          "",
          "",
          ""
        ]
      }
    },
    {
      "country": "United States",
      "artist_name": "economy elite",
      "currency": "USD",
      "amount_paid_fmt": "$1",
      "item_price": 0,
      "slug_type": "a",
      "item_description": "late night ramen",
      "amount_paid": 1,
      "art_id": 1248884204,
      "art_url": "https://f4.bcbits.com/img/a1248884204_7.jpg",
      "amount_paid_usd": 1,
      "url": "https://economyelite.bandcamp.com/album/late-night-ramen",
      "item_type": "a",
      "country_code": "us",
      "utc_date": 1654197068.81191,
      "details": {
        "type": "album",
        "stories": [
          "",
          "",
          "",
          "",
          "",
          "",
          ""
        ]
      }
    },
    {
      "country": "United States",
      "artist_name": "economy elite",
      "currency": "USD",
      "amount_paid_fmt": "$1",
      "item_price": 0,
      "slug_type": "a",
      "amount_paid": 1,
      "art_id": 1554066566,
      "art_url": "https://f4.bcbits.com/img/a1554066566_7.jpg",
      "amount_paid_usd": 1,
      "url": "https://midnightramen.bandcamp.com/album/late-night-ramen",
      "item_description": "late night ramen",
      "item_type": "a",
      "country_code": "us",
      "utc_date": 1654206494.37255,
      "details": {
        "type": "album",
        "stories": [
          "",
          "",
          "",
          "",
          "",
          "",
          ""
        ]
      }
    },
    {
      "country": "Germany",
      "amount_paid_fmt": "€0.50",
      "artist_name": "ECTOGASMICS (Parvati Records)",
      "currency": "EUR",
      "item_price": 0,
      "slug_type": "a",
      "amount_paid": 0.5,
      "art_url": "https://f4.bcbits.com/img/a4142516541_7.jpg",
      "item_type": "a",
      "amount_paid_usd": 0.54,
      "art_id": 4142516541,
      "url": "https://beatspace-parvati.bandcamp.com/album/i-need-a-computer",
      "country_code": "de",
      "item_description": "I NEED A COMPUTER",
      "utc_date": 1653693379.34441,
      "details": {
        "type": "track",
        "stories": [
          "",
          "",
          ""
        ]
      }
    },
    {
      "country": "United States",
      "amount_paid_fmt": "$20",
      "artist_name": "Ed Harrison",
      "currency": "USD",
      "item_price": 0,
      "slug_type": "a",
      "amount_paid": 20,
      "item_description": "ntremixed02",
      "amount_over_fmt": "$20",
      "art_url": "https://f4.bcbits.com/img/a3870390671_7.jpg",
      "item_type": "a",
      "amount_paid_usd": 20,
      "art_id": 3870390671,
      "url": "https://edharrison.bandcamp.com/album/ntremixed02",
      "country_code": "us",
      "utc_date": 1653659053.09433,
      "details": {
        "type": "album",
        "stories": [
          "electronic",
          "idm",
          "ambient",
          "cyberpunk",
          "dnb",
          "drum and bass",
          "electronica",
          "liquid dnb",
          "Sydney"
        ]
      }
    },
    {
      "utc_date": 1653712730.86349,
      "country": "United States",
      "artist_name": "Ed Harrison",
      "currency": "USD",
      "amount_paid_fmt": "$1",
      "item_price": 0,
      "slug_type": "a",
      "amount_paid": 1,
      "art_id": 3957505460,
      "item_description": "0edit",
      "url": "https://edharrison.bandcamp.com/album/0edit",
      "country_code": "us",
      "art_url": "https://f4.bcbits.com/img/a3957505460_7.jpg",
      "item_type": "a",
      "amount_paid_usd": 1,
      "details": {
        "type": "album",
        "stories": [
          "",
          "",
          "",
          "",
          "",
          ""
        ]
      }
    },
    {
      "utc_date": 1653713387.77559,
      "country": "United States",
      "artist_name": "Ed Harrison",
      "currency": "USD",
      "amount_paid_fmt": "$1",
      "item_price": 0,
      "slug_type": "a",
      "amount_paid": 1,
      "art_id": 994444672,
      "url": "https://edharrison.bandcamp.com/album/neotokyo-gsdf",
      "country_code": "us",
      "art_url": "https://f4.bcbits.com/img/a0994444672_7.jpg",
      "item_type": "a",
      "amount_paid_usd": 1,
      "item_description": "Neotokyo GSDF",
      "details": {
        "type": "album",
        "stories": [
          "",
          "",
          "",
          "",
          "",
          "",
          "",
          "",
          "",
          "",
          "",
          ""
        ]
      }
    },
    {
      "country": "Netherlands",
      "artist_name": "Ed Harrison",
      "currency": "USD",
      "amount_paid_fmt": "$10",
      "item_price": 0,
      "slug_type": "a",
      "amount_paid": 10,
      "art_id": 3254388485,
      "amount_over_fmt": "$10",
      "art_url": "https://f4.bcbits.com/img/a3254388485_7.jpg",
      "amount_paid_usd": 10,
      "url": "https://edharrison.bandcamp.com/album/neotokyo-remixed-01",
      "item_description": "Neotokyo Remixed 01",
      "item_type": "a",
      "country_code": "nl",
      "utc_date": 1654117038.48149,
      "details": {
        "type": "album",
        "stories": [
          "",
          "",
          "",
          "",
          "",
          "",
          ""
        ]
      }
    },
    {
      "country": "United States",
      "artist_name": "Ed Harrison",
      "currency": "USD",
      "amount_paid_fmt": "$20",
      "item_price": 0,
      "slug_type": "a",
      "amount_paid": 20,
      "art_id": 93578376,
      "amount_over_fmt": "$20",
      "art_url": "https://f4.bcbits.com/img/a0093578376_7.jpg",
      "item_description": "Neotokyo: Appendix",
      "amount_paid_usd": 20,
      "url": "https://edharrison.bandcamp.com/album/neotokyo-appendix",
      "item_type": "a",
      "country_code": "us",
      "utc_date": 1654301595.06009,
      "details": {
        "type": "album",
        "stories": [
          "",
          "",
          "",
          "",
          "",
          ""
        ]
      }
    },
    {
      "item_type": "a",
      "country_code": "au",
      "item_description": "La Di Doh Free Corp version",
      "utc_date": 1654322030.95124,
      "country": "Australia",
      "artist_name": "Ed Kuepper",
      "currency": "AUD",
      "amount_paid_fmt": "$1 AUD",
      "item_price": 0,
      "slug_type": "a",
      "amount_paid": 1,
      "url": "https://edkuepper1.bandcamp.com/album/la-di-doh-free-corp-version",
      "art_id": 1906176642,
      "art_url": "https://f4.bcbits.com/img/a1906176642_7.jpg",
      "amount_paid_usd": 0.72,
      "details": {
        "type": "album",
        "stories": [
          "",
          "",
          "",
          "",
          "",
          "",
          "",
          "",
          "",
          "",
          ""
        ]
      }
    },
    {
      "item_description": "Anywhere People EP",
      "country": "United States",
      "artist_name": "Edamame",
      "currency": "USD",
      "amount_paid_fmt": "$3",
      "item_price": 0,
      "slug_type": "a",
      "amount_paid": 3,
      "art_id": 3434318499,
      "amount_over_fmt": "$3",
      "art_url": "https://f4.bcbits.com/img/a3434318499_7.jpg",
      "amount_paid_usd": 3,
      "url": "https://edamame.bandcamp.com/album/anywhere-people-ep",
      "item_type": "a",
      "country_code": "us",
      "utc_date": 1654298269.4263,
      "details": {
        "type": "album",
        "stories": [
          "",
          "",
          "",
          "",
          "",
          "",
          "",
          "",
          "",
          "",
          "",
          "",
          "",
          "",
          "",
          ""
        ]
      }
    },
    {
      "amount_paid": 0.5,
      "country_code": "us",
      "art_url": "https://f4.bcbits.com/img/a2649472251_7.jpg",
      "item_description": "Various Vol.1",
      "slug_type": "a",
      "amount_paid_usd": 0.53,
      "country": "United States",
      "artist_name": "Eddy Larkin",
      "currency": "EUR",
      "utc_date": 1655076353.94744,
      "url": "https://eddylarkin.bandcamp.com/album/various-vol-1",
      "art_id": 2649472251,
      "amount_paid_fmt": "€0.50",
      "item_type": "a",
      "item_price": 0,
      "details": {
        "type": "album",
        "stories": [
          "",
          "",
          "",
          "",
          "",
          "",
          ""
        ]
      }
    },
    {
      "country": "Canada",
      "artist_name": "eden pipe camp",
      "currency": "CAD",
      "amount_paid_fmt": "$5 CAD",
      "item_price": 0,
      "slug_type": "a",
      "amount_paid": 5,
      "art_id": 424607616,
      "amount_over_fmt": "$5",
      "art_url": "https://f4.bcbits.com/img/a0424607616_7.jpg",
      "amount_paid_usd": 3.97,
      "url": "https://edenpipecamp.bandcamp.com/album/bright-hope-strangely-dim",
      "item_type": "a",
      "country_code": "ca",
      "utc_date": 1654292250.18662,
      "item_description": "bright hope / strangely dim",
      "details": {
        "type": "album",
        "stories": [
          "",
          "",
          "",
          "",
          ""
        ]
      }
    },
    {
      "amount_paid": 1,
      "country_code": "jp",
      "art_url": "https://f4.bcbits.com/img/a2046429222_7.jpg",
      "slug_type": "a",
      "amount_paid_usd": 1,
      "country": "Japan",
      "artist_name": "Edifice",
      "currency": "USD",
      "utc_date": 1655120658.19635,
      "url": "https://dialatedmusicproductions.bandcamp.com/album/soundtrack",
      "art_id": 2046429222,
      "amount_paid_fmt": "$1",
      "item_type": "a",
      "item_price": 0,
      "item_description": "Soundtrack",
      "details": {
        "type": "track",
        "stories": [
          "",
          "",
          "",
          "",
          "",
          "",
          "",
          "",
          "",
          "",
          "",
          "",
          "",
          "",
          "",
          ""
        ]
      }
    },
    {
      "item_type": "a",
      "country_code": "us",
      "utc_date": 1654310221.46096,
      "country": "United States",
      "artist_name": "Editrix",
      "currency": "USD",
      "amount_paid_fmt": "$2",
      "item_price": 0,
      "slug_type": "a",
      "amount_paid": 2,
      "url": "https://editrix.bandcamp.com/album/talk-to-me",
      "art_id": 3920276105,
      "art_url": "https://f4.bcbits.com/img/a3920276105_7.jpg",
      "amount_paid_usd": 2,
      "item_description": "Talk to Me",
      "details": {
        "type": "album",
        "stories": [
          "",
          "",
          "",
          "",
          "",
          "",
          "",
          "",
          "",
          ""
        ]
      }
    },
    {
      "amount_paid": 5,
      "country_code": "us",
      "art_url": "https://f4.bcbits.com/img/a1566186127_7.jpg",
      "slug_type": "a",
      "amount_over_fmt": "$5",
      "amount_paid_usd": 5,
      "country": "United States",
      "artist_name": "EDO",
      "currency": "USD",
      "utc_date": 1655126689.37373,
      "url": "https://nightofthepalemoon.bandcamp.com/album/without-emotions-np-iii",
      "item_description": "Without Emotions (NP-III)",
      "art_id": 1566186127,
      "amount_paid_fmt": "$5",
      "item_type": "a",
      "item_price": 0,
      "details": {
        "type": "album",
        "stories": [
          "",
          "",
          "",
          "",
          "",
          "",
          "",
          "",
          "",
          "",
          "",
          ""
        ]
      }
    },
    {
      "item_type": "a",
      "country_code": "gb",
      "utc_date": 1654439448.29824,
      "country": "United Kingdom",
      "artist_name": "Edward Cybered",
      "currency": "EUR",
      "amount_paid_fmt": "€0.50",
      "item_description": "Cybered — Forget Your Past (2013) album | FREE Download",
      "item_price": 0,
      "slug_type": "a",
      "amount_paid": 0.5,
      "url": "https://cybered.bandcamp.com/album/cybered-forget-your-past-2013-album-free-download",
      "art_id": 823132910,
      "art_url": "https://f4.bcbits.com/img/a0823132910_7.jpg",
      "amount_paid_usd": 0.54,
      "details": {
        "type": "album",
        "stories": [
          "",
          "",
          "",
          "",
          "",
          "",
          "",
          "",
          "",
          ""
        ]
      }
    },
    {
      "item_description": "Cybered - Bunker | EP | tracks (2001-2005) | FREE Download",
      "item_type": "a",
      "country_code": "gb",
      "utc_date": 1654439486.21691,
      "country": "United Kingdom",
      "artist_name": "Edward Cybered",
      "currency": "EUR",
      "amount_paid_fmt": "€0.50",
      "item_price": 0,
      "slug_type": "a",
      "amount_paid": 0.5,
      "url": "https://cybered.bandcamp.com/album/cybered-bunker-ep-tracks-2001-2005-free-download",
      "art_id": 2150732764,
      "art_url": "https://f4.bcbits.com/img/a2150732764_7.jpg",
      "amount_paid_usd": 0.54,
      "details": {
        "type": "album",
        "stories": [
          "",
          "",
          "",
          "",
          "",
          "",
          ""
        ]
      }
    },
    {
      "utc_date": 1653754899.88023,
      "item_description": "Tanith & The Lion Tree (2020 Remaster)",
      "country": "Slovakia",
      "artist_name": "Edward Ka-Spel",
      "currency": "USD",
      "amount_paid_fmt": "$2",
      "item_price": 0,
      "slug_type": "a",
      "amount_paid": 2,
      "art_id": 4193214619,
      "url": "https://edwardka-spel.bandcamp.com/album/tanith-the-lion-tree-2020-remaster",
      "country_code": "sk",
      "art_url": "https://f4.bcbits.com/img/a4193214619_7.jpg",
      "item_type": "a",
      "amount_paid_usd": 2,
      "details": {
        "type": "album",
        "stories": [
          "",
          "",
          ""
        ]
      }
    },
    {
      "utc_date": 1653765432.33935,
      "item_description": "Tales From The Trenches",
      "country": "United States",
      "artist_name": "Edward Ka-Spel",
      "currency": "USD",
      "amount_paid_fmt": "$6",
      "item_price": 0,
      "slug_type": "a",
      "amount_paid": 6,
      "art_id": 2156218348,
      "url": "https://edwardka-spel.bandcamp.com/album/tales-from-the-trenches",
      "country_code": "us",
      "amount_over_fmt": "$6",
      "art_url": "https://f4.bcbits.com/img/a2156218348_7.jpg",
      "item_type": "a",
      "amount_paid_usd": 6,
      "details": {
        "type": "album",
        "stories": [
          "",
          "",
          ""
        ]
      }
    },
    {
      "country": "United Kingdom",
      "artist_name": "Edward Ka-Spel",
      "currency": "USD",
      "amount_paid_fmt": "$8.39",
      "item_price": 0,
      "slug_type": "a",
      "amount_paid": 8.39,
      "art_id": 1878726660,
      "amount_over_fmt": "$8.39",
      "art_url": "https://f4.bcbits.com/img/a1878726660_7.jpg",
      "amount_paid_usd": 8.39,
      "url": "https://edwardka-spel.bandcamp.com/album/conspiracy-of-pylons",
      "item_type": "a",
      "country_code": "gb",
      "utc_date": 1654194118.21927,
      "item_description": "Conspiracy Of Pylons",
      "details": {
        "type": "album",
        "stories": [
          "",
          "",
          ""
        ]
      }
    },
    {
      "amount_paid": 1,
      "country_code": "us",
      "art_url": "https://f4.bcbits.com/img/a0256913974_7.jpg",
      "item_description": "10 To The Power Of 9 Chapters III & IV",
      "slug_type": "a",
      "amount_paid_usd": 1,
      "country": "United States",
      "artist_name": "Edward Ka-Spel",
      "currency": "USD",
      "utc_date": 1655061036.15369,
      "url": "https://legendarypinkdots1.bandcamp.com/album/10-to-the-power-of-9-chapters-iii-iv",
      "art_id": 256913974,
      "amount_paid_fmt": "$1",
      "item_type": "a",
      "item_price": 0,
      "details": {
        "type": "album",
        "stories": [
          "",
          "",
          ""
        ]
      }
    },
    {
      "amount_paid": 0.5,
      "country_code": "pt",
      "art_url": "https://f4.bcbits.com/img/a1491829696_7.jpg",
      "slug_type": "a",
      "amount_paid_usd": 0.53,
      "country": "Portugal",
      "artist_name": "Edward Sol",
      "currency": "EUR",
      "utc_date": 1655069752.62448,
      "url": "https://edwardsol.bandcamp.com/album/cold-breath",
      "art_id": 1491829696,
      "amount_paid_fmt": "€0.50",
      "item_description": "Cold Breath",
      "item_type": "a",
      "item_price": 0,
      "details": {
        "type": "track",
        "stories": [
          "",
          "",
          "",
          "",
          "",
          ""
        ]
      }
    },
    {
      "item_description": "GREEN SOUNDS -Raw Label-",
      "amount_paid": 1,
      "country_code": "gb",
      "art_url": "https://f4.bcbits.com/img/a2974302199_7.jpg",
      "slug_type": "a",
      "amount_paid_usd": 1.05,
      "country": "United Kingdom",
      "artist_name": "eebrozgi",
      "currency": "EUR",
      "utc_date": 1655103693.70528,
      "url": "https://eebrozgi.bandcamp.com/album/green-sounds-raw-label",
      "art_id": 2974302199,
      "amount_paid_fmt": "€1",
      "item_type": "a",
      "item_price": 0,
      "details": {
        "type": "album",
        "stories": [
          "",
          "",
          "",
          "",
          "",
          "",
          "",
          "",
          "",
          "",
          ""
        ]
      }
    },
    {
      "item_description": "Eeuwig",
      "utc_date": 1653735326.4743,
      "country": "United Kingdom",
      "artist_name": "Eeuwig",
      "currency": "EUR",
      "amount_paid_fmt": "€0.50",
      "item_price": 0,
      "slug_type": "a",
      "amount_paid": 0.5,
      "art_id": 2408079084,
      "url": "https://eeuwigblackmetal.bandcamp.com/album/eeuwig",
      "country_code": "gb",
      "art_url": "https://f4.bcbits.com/img/a2408079084_7.jpg",
      "item_type": "a",
      "amount_paid_usd": 0.54,
      "details": {
        "type": "album",
        "stories": [
          "",
          "",
          "",
          "",
          "",
          ""
        ]
      }
    },
    {
      "item_type": "a",
      "country_code": "us",
      "utc_date": 1654432262.59536,
      "country": "United States",
      "artist_name": "Eezy Seven",
      "currency": "USD",
      "amount_paid_fmt": "$30",
      "item_description": "The Loud Harmony 4: Love, Rock & Harmony",
      "item_price": 0,
      "slug_type": "a",
      "amount_paid": 30,
      "url": "https://eezyseven.bandcamp.com/album/the-loud-harmony-4-love-rock-harmony",
      "art_id": 725620265,
      "amount_over_fmt": "$30",
      "art_url": "https://f4.bcbits.com/img/a0725620265_7.jpg",
      "amount_paid_usd": 30,
      "details": {
        "type": "album",
        "stories": [
          "",
          "",
          "",
          "",
          "",
          "",
          "",
          "",
          "",
          "",
          "",
          "",
          "",
          ""
        ]
      }
    },
    {
      "amount_paid": 1,
      "country_code": "hu",
      "art_url": "https://f4.bcbits.com/img/a2367209098_7.jpg",
      "slug_type": "a",
      "amount_paid_usd": 1.04,
      "country": "Hungary",
      "artist_name": "EF",
      "currency": "EUR",
      "utc_date": 1655184023.9878,
      "url": "https://efmusicsweden.bandcamp.com/album/delusions-of-grandeur",
      "art_id": 2367209098,
      "amount_paid_fmt": "€1",
      "item_type": "a",
      "item_price": 0,
      "item_description": "Delusions of Grandeur",
      "details": {
        "type": "album",
        "stories": [
          "",
          "",
          "",
          "",
          ""
        ]
      }
    },
    {
      "item_description": "Resistance (2022)",
      "item_type": "a",
      "country_code": "us",
      "utc_date": 1654372126.77939,
      "country": "United States",
      "artist_name": "EffaTha & The Projekt KaTholiban",
      "currency": "USD",
      "amount_paid_fmt": "$1",
      "item_price": 0,
      "slug_type": "a",
      "amount_paid": 1,
      "url": "https://effatha.bandcamp.com/album/resistance-2022",
      "art_id": 3833291896,
      "art_url": "https://f4.bcbits.com/img/a3833291896_7.jpg",
      "amount_paid_usd": 1,
      "details": {
        "type": "album",
        "stories": [
          "",
          "",
          "",
          "",
          "",
          "",
          ""
        ]
      }
    },
    {
      "amount_paid": 1,
      "country_code": "au",
      "art_url": "https://f4.bcbits.com/img/a1691186608_7.jpg",
      "slug_type": "a",
      "amount_paid_usd": 1.05,
      "country": "Australia",
      "artist_name": "EGG IDIOT",
      "currency": "EUR",
      "utc_date": 1655120357.87275,
      "url": "https://eggidiot.bandcamp.com/album/egg-idiot",
      "art_id": 1691186608,
      "amount_paid_fmt": "€1",
      "item_type": "a",
      "item_price": 0,
      "item_description": "EGG IDIOT",
      "details": {
        "type": "track",
        "stories": [
          "",
          "",
          "",
          "",
          "",
          "",
          ""
        ]
      }
    },
    {
      "item_type": "a",
      "country_code": "us",
      "utc_date": 1654362270.15922,
      "item_description": "PARTY CITY",
      "country": "United States",
      "artist_name": "EGGPRIEST",
      "currency": "USD",
      "amount_paid_fmt": "$2",
      "item_price": 0,
      "slug_type": "a",
      "amount_paid": 2,
      "url": "https://eggpriest.bandcamp.com/album/party-city",
      "art_id": 526407616,
      "art_url": "https://f4.bcbits.com/img/a0526407616_7.jpg",
      "amount_paid_usd": 2,
      "details": {
        "type": "album",
        "stories": [
          "",
          "",
          "",
          "",
          "",
          "",
          "",
          "",
          "",
          "",
          ""
        ]
      }
    },
    {
      "utc_date": 1653878110.73889,
      "country": "United States",
      "artist_name": "Ego Death",
      "currency": "USD",
      "amount_paid_fmt": "$1",
      "item_price": 0,
      "slug_type": "a",
      "amount_paid": 1,
      "art_id": 3584675339,
      "url": "https://theegodeath.bandcamp.com/album/demo",
      "country_code": "us",
      "art_url": "https://f4.bcbits.com/img/a3584675339_7.jpg",
      "item_type": "a",
      "amount_paid_usd": 1,
      "item_description": "DEMO",
      "details": {
        "type": "album",
        "stories": [
          "",
          "",
          "",
          "",
          "",
          "",
          "",
          "",
          "",
          "",
          ""
        ]
      }
    },
    {
      "utc_date": 1653866609.65549,
      "country": "United States",
      "artist_name": "Ego Fix",
      "currency": "USD",
      "amount_paid_fmt": "$4",
      "item_price": 0,
      "slug_type": "a",
      "amount_paid": 4,
      "art_id": 3841092884,
      "url": "https://mortvillenoise.bandcamp.com/album/total-filth-squad-discography-1995-1997",
      "country_code": "us",
      "amount_over_fmt": "$4",
      "art_url": "https://f4.bcbits.com/img/a3841092884_7.jpg",
      "item_description": "TOTAL FILTH SQUAD Discography 1995-1997",
      "item_type": "a",
      "amount_paid_usd": 4,
      "details": {
        "type": "track",
        "stories": [
          "",
          "",
          "",
          ""
        ]
      }
    },
    {
      "utc_date": 1653713008.01934,
      "country": "United States",
      "artist_name": "EGOLESS",
      "currency": "EUR",
      "amount_paid_fmt": "€0.50",
      "item_price": 0,
      "item_description": "Selected Works 2009 - 2012",
      "slug_type": "a",
      "amount_paid": 0.5,
      "art_id": 4246837276,
      "url": "https://egoless.bandcamp.com/album/selected-works-2009-2012",
      "country_code": "us",
      "art_url": "https://f4.bcbits.com/img/a4246837276_7.jpg",
      "item_type": "a",
      "amount_paid_usd": 0.54,
      "details": {
        "type": "album",
        "stories": [
          "",
          "",
          "",
          "",
          "",
          "",
          "",
          "",
          "",
          "",
          "",
          ""
        ]
      }
    },
    {
      "amount_paid": 4,
      "country_code": "cz",
      "art_url": "https://f4.bcbits.com/img/a0830521688_7.jpg",
      "item_description": "Solidarity in Dub",
      "slug_type": "a",
      "amount_over_fmt": "€4",
      "amount_paid_usd": 4.19,
      "country": "Czech Republic",
      "artist_name": "EGOLESS",
      "currency": "EUR",
      "utc_date": 1655123104.92465,
      "url": "https://egoless.bandcamp.com/album/solidarity-in-dub",
      "art_id": 830521688,
      "amount_paid_fmt": "€4",
      "item_type": "a",
      "item_price": 0,
      "details": {
        "type": "album",
        "stories": [
          "",
          "",
          "",
          "",
          "",
          "",
          "",
          "",
          "",
          "",
          "",
          ""
        ]
      }
    },
    {
      "item_type": "a",
      "country_code": "gb",
      "utc_date": 1654341577.29196,
      "country": "United Kingdom",
      "artist_name": "Egregore Collective",
      "currency": "EUR",
      "amount_paid_fmt": "€0.50",
      "item_price": 0,
      "slug_type": "a",
      "amount_paid": 0.5,
      "url": "https://egregorecollective.bandcamp.com/album/egfree004-3k-thank-you-ep",
      "art_id": 4038080490,
      "art_url": "https://f4.bcbits.com/img/a4038080490_7.jpg",
      "amount_paid_usd": 0.54,
      "item_description": "EGFREE004 - 3K Thank You EP",
      "details": {
        "type": "track",
        "stories": [
          "",
          "",
          "",
          "",
          "",
          "",
          "",
          "",
          "",
          ""
        ]
      }
    },
    {
      "country": "United States",
      "amount_paid_fmt": "€1",
      "artist_name": "Eguana",
      "currency": "EUR",
      "item_price": 0,
      "slug_type": "a",
      "amount_paid": 1,
      "art_url": "https://f4.bcbits.com/img/a1286238729_7.jpg",
      "item_type": "a",
      "amount_paid_usd": 1.07,
      "art_id": 1286238729,
      "url": "https://eguana.bandcamp.com/album/abandoned-24bit",
      "country_code": "us",
      "utc_date": 1653689320.05451,
      "item_description": "Abandoned (24bit)",
      "details": {
        "type": "track",
        "stories": [
          "",
          "",
          "",
          "",
          "",
          "",
          "",
          "",
          ""
        ]
      }
    },
    {
      "amount_paid": 3,
      "country_code": "us",
      "art_url": "https://f4.bcbits.com/img/a0465303280_7.jpg",
      "slug_type": "a",
      "amount_over_fmt": "€3",
      "amount_paid_usd": 3.15,
      "country": "United States",
      "item_description": "Lure Me",
      "artist_name": "Eguana",
      "currency": "EUR",
      "utc_date": 1655068867.40825,
      "url": "https://cosmicleaf.bandcamp.com/album/lure-me",
      "art_id": 465303280,
      "amount_paid_fmt": "€3",
      "item_type": "a",
      "item_price": 0,
      "details": {
        "type": "track",
        "stories": [
          "",
          "",
          "",
          "",
          "",
          "",
          "",
          "",
          "",
          "",
          "",
          "",
          "",
          "",
          "",
          ""
        ]
      }
    },
    {
      "amount_paid": 2.22,
      "country_code": "us",
      "art_url": "https://f4.bcbits.com/img/a1133272056_7.jpg",
      "item_description": "Abandoned (24bit)",
      "slug_type": "a",
      "amount_over_fmt": "€2.22",
      "amount_paid_usd": 2.33,
      "country": "United States",
      "artist_name": "Eguana",
      "currency": "EUR",
      "utc_date": 1655092068.839,
      "url": "https://plexusmusic.bandcamp.com/album/abandoned-24bit",
      "art_id": 1133272056,
      "amount_paid_fmt": "€2.22",
      "item_type": "a",
      "item_price": 0,
      "details": {
        "type": "track",
        "stories": [
          "",
          "",
          "",
          "",
          "",
          "",
          "",
          "",
          ""
        ]
      }
    },
    {
      "amount_paid": 1,
      "country_code": "gb",
      "art_url": "https://f4.bcbits.com/img/a2943915882_7.jpg",
      "slug_type": "a",
      "amount_paid_usd": 1.04,
      "country": "United Kingdom",
      "artist_name": "Eif",
      "currency": "EUR",
      "utc_date": 1655126769.71242,
      "url": "https://eiff.bandcamp.com/album/too-pastiche",
      "item_description": "Too Pastiche",
      "art_id": 2943915882,
      "amount_paid_fmt": "€1",
      "item_type": "a",
      "item_price": 0,
      "details": {
        "type": "album",
        "stories": [
          "",
          "",
          "",
          "",
          "",
          ""
        ]
      }
    },
    {
      "item_type": "a",
      "country_code": "jp",
      "utc_date": 1654307855.89741,
      "country": "Japan",
      "artist_name": "Eighaphoria and Bloodclot",
      "currency": "USD",
      "amount_paid_fmt": "$2.50",
      "item_price": 0,
      "slug_type": "a",
      "amount_paid": 2.5,
      "url": "https://reactionary.bandcamp.com/album/react-17-soundbwoy-murderer",
      "art_id": 991141989,
      "amount_over_fmt": "$2.50",
      "art_url": "https://f4.bcbits.com/img/a0991141989_7.jpg",
      "amount_paid_usd": 2.5,
      "item_description": "REACT​:​17 SOUNDBWOY MURDERER",
      "details": {
        "type": "track",
        "stories": [
          "",
          "",
          "",
          "",
          "",
          "",
          ""
        ]
      }
    },
    {
      "amount_paid": 4,
      "country_code": "ca",
      "art_url": "https://f4.bcbits.com/img/a3009084745_7.jpg",
      "slug_type": "a",
      "amount_over_fmt": "$4",
      "amount_paid_usd": 3.13,
      "country": "Canada",
      "artist_name": "Eight Foot Sixteen",
      "currency": "CAD",
      "utc_date": 1655080849.5831,
      "url": "https://eightfootsixteen.bandcamp.com/album/ep1",
      "item_description": "EP1",
      "art_id": 3009084745,
      "amount_paid_fmt": "$4 CAD",
      "item_type": "a",
      "item_price": 0,
      "details": {
        "type": "album",
        "stories": [
          "",
          "",
          "",
          ""
        ]
      }
    },
    {
      "country": "United Kingdom",
      "artist_name": "Einstellung",
      "currency": "GBP",
      "amount_paid_fmt": "£4",
      "item_price": 0,
      "slug_type": "a",
      "item_description": "Our Fence Is Electric (EP)",
      "amount_paid": 4,
      "art_id": 2024876593,
      "amount_over_fmt": "£4",
      "art_url": "https://f4.bcbits.com/img/a2024876593_7.jpg",
      "amount_paid_usd": 4.99,
      "url": "https://einstellung.bandcamp.com/album/our-fence-is-electric-ep",
      "item_type": "a",
      "country_code": "gb",
      "utc_date": 1654146661.05573,
      "details": {
        "type": "track",
        "stories": [
          "",
          "",
          "",
          "",
          "",
          "",
          "",
          "",
          "",
          "",
          "",
          "",
          "",
          "",
          "",
          "",
          ""
        ]
      }
    },
    {
      "item_description": "DATASEED",
      "country": "United States",
      "artist_name": "Eir Mazur",
      "currency": "USD",
      "amount_paid_fmt": "$1.01",
      "item_price": 0,
      "slug_type": "a",
      "amount_paid": 1.01,
      "art_id": 1869224506,
      "art_url": "https://f4.bcbits.com/img/a1869224506_7.jpg",
      "amount_paid_usd": 1.01,
      "url": "https://mzzr.bandcamp.com/album/dataseed",
      "item_type": "a",
      "country_code": "us",
      "utc_date": 1654274008.10172,
      "details": {
        "type": "album",
        "stories": [
          "",
          "",
          "",
          "",
          "",
          "",
          "",
          "",
          "",
          "",
          "",
          ""
        ]
      }
    },
    {
      "utc_date": 1653753868.8463,
      "country": "Canada",
      "artist_name": "Eiyn Sof",
      "currency": "CAD",
      "amount_paid_fmt": "$10 CAD",
      "item_price": 0,
      "slug_type": "a",
      "amount_paid": 10,
      "art_id": 1510702288,
      "url": "https://eiynsof.bandcamp.com/album/my-sail-is-an-ancient-wing",
      "country_code": "ca",
      "amount_over_fmt": "$10",
      "art_url": "https://f4.bcbits.com/img/a1510702288_7.jpg",
      "item_description": "My Sail Is An Ancient Wing",
      "item_type": "a",
      "amount_paid_usd": 7.86,
      "details": {
        "type": "album",
        "stories": [
          "",
          "",
          "",
          "",
          ""
        ]
      }
    },
    {
      "country": "Norway",
      "amount_paid_fmt": "$2 CAD",
      "currency": "CAD",
      "artist_name": "Eiyn Sof",
      "item_price": 0,
      "slug_type": "a",
      "amount_paid": 2,
      "art_id": 72503015,
      "item_description": "Spectral Queen Mini EP",
      "art_url": "https://f4.bcbits.com/img/a0072503015_7.jpg",
      "url": "https://eiynsof.bandcamp.com/album/spectral-queen-mini-ep",
      "amount_paid_usd": 1.59,
      "country_code": "no",
      "item_type": "a",
      "utc_date": 1654235576.1688,
      "details": {
        "type": "album",
        "stories": [
          "",
          "",
          "",
          "",
          ""
        ]
      }
    },
    {
      "utc_date": 1653813773.86426,
      "country": "Belgium",
      "artist_name": "Ekhe",
      "currency": "GBP",
      "item_description": "Lost His Shit",
      "amount_paid_fmt": "£5",
      "item_price": 0,
      "slug_type": "a",
      "amount_paid": 5,
      "art_id": 945105307,
      "url": "https://spookyshit.bandcamp.com/album/lost-his-shit",
      "country_code": "be",
      "amount_over_fmt": "£5",
      "art_url": "https://f4.bcbits.com/img/a0945105307_7.jpg",
      "item_type": "a",
      "amount_paid_usd": 6.31,
      "details": {
        "type": "track",
        "stories": [
          ""
        ]
      }
    },
    {
      "utc_date": 1653771004.73266,
      "country": "United States",
      "artist_name": "Ekoplex",
      "currency": "CAD",
      "amount_paid_fmt": "$3 CAD",
      "item_price": 0,
      "slug_type": "a",
      "item_description": "Discovering The Ancient",
      "amount_paid": 3,
      "art_id": 1397620598,
      "url": "https://ekoplex.bandcamp.com/album/discovering-the-ancient",
      "country_code": "us",
      "amount_over_fmt": "$3",
      "art_url": "https://f4.bcbits.com/img/a1397620598_7.jpg",
      "item_type": "a",
      "amount_paid_usd": 2.36,
      "details": {
        "type": "album",
        "stories": [
          "",
          "",
          "",
          "",
          ""
        ]
      }
    },
    {
      "utc_date": 1653768931.42196,
      "country": "Germany",
      "artist_name": "Ekranoplan",
      "currency": "EUR",
      "amount_paid_fmt": "€1",
      "item_price": 0,
      "slug_type": "a",
      "amount_paid": 1,
      "art_id": 3706481163,
      "url": "https://ekranoplandoomgrind.bandcamp.com/album/ekranoplan",
      "country_code": "de",
      "item_description": "Ekranoplan",
      "art_url": "https://f4.bcbits.com/img/a3706481163_7.jpg",
      "item_type": "a",
      "amount_paid_usd": 1.07,
      "details": {
        "type": "album",
        "stories": [
          "",
          "",
          "",
          "",
          "",
          "",
          ""
        ]
      }
    },
    {
      "country": "Greece",
      "amount_paid_fmt": "£0.50",
      "artist_name": "Ekrixi",
      "currency": "GBP",
      "item_price": 0,
      "slug_type": "a",
      "amount_paid": 0.5,
      "art_url": "https://f4.bcbits.com/img/a0898033424_7.jpg",
      "item_type": "a",
      "amount_paid_usd": 0.63,
      "art_id": 898033424,
      "item_description": "Ékrixi",
      "url": "https://ekrixi.bandcamp.com/album/krixi",
      "country_code": "gr",
      "utc_date": 1653682037.84114,
      "details": {
        "type": "album",
        "stories": [
          "",
          "",
          "",
          "",
          "",
          ""
        ]
      }
    },
    {
      "utc_date": 1653815235.66983,
      "country": "Germany",
      "artist_name": "EKULU",
      "currency": "USD",
      "amount_paid_fmt": "$5",
      "item_price": 0,
      "item_description": "Unscrew My Head",
      "slug_type": "a",
      "amount_paid": 5,
      "art_id": 1623797637,
      "url": "https://ekulu.bandcamp.com/album/unscrew-my-head",
      "country_code": "de",
      "amount_over_fmt": "$5",
      "art_url": "https://f4.bcbits.com/img/a1623797637_7.jpg",
      "item_type": "a",
      "amount_paid_usd": 5,
      "details": {
        "type": "album",
        "stories": [
          "",
          "",
          "",
          "",
          ""
        ]
      }
    },
    {
      "utc_date": 1653780845.14791,
      "country": "Mexico",
      "item_description": "FREEBIES DRILL EDITION",
      "artist_name": "EL BLANCO NINO",
      "currency": "USD",
      "amount_paid_fmt": "$1",
      "item_price": 0,
      "slug_type": "a",
      "amount_paid": 1,
      "art_id": 183956817,
      "url": "https://elblanconino.bandcamp.com/album/freebies-drill-edition",
      "country_code": "mx",
      "art_url": "https://f4.bcbits.com/img/a0183956817_7.jpg",
      "item_type": "a",
      "amount_paid_usd": 1,
      "details": {
        "type": "album",
        "stories": [
          "",
          "",
          "",
          "",
          "",
          "",
          ""
        ]
      }
    },
    {
      "item_type": "a",
      "country_code": "au",
      "utc_date": 1654422371.49789,
      "country": "Australia",
      "artist_name": "El Búho",
      "currency": "EUR",
      "amount_paid_fmt": "€4",
      "item_price": 0,
      "slug_type": "a",
      "item_description": "Tamoanchan EP",
      "amount_paid": 4,
      "url": "https://elbuho.bandcamp.com/album/tamoanchan-ep",
      "art_id": 1042455313,
      "amount_over_fmt": "€4",
      "art_url": "https://f4.bcbits.com/img/a1042455313_7.jpg",
      "amount_paid_usd": 4.29,
      "details": {
        "type": "album",
        "stories": [
          "",
          "",
          "",
          "",
          "",
          "",
          "",
          "",
          "",
          "",
          ""
        ]
      }
    },
    {
      "amount_paid": 3,
      "country_code": "us",
      "art_url": "https://f4.bcbits.com/img/a0921079384_7.jpg",
      "slug_type": "a",
      "amount_over_fmt": "€3",
      "amount_paid_usd": 3.15,
      "country": "United States",
      "artist_name": "El Búho",
      "currency": "EUR",
      "item_description": "A Guide to the Birds of South America EP",
      "utc_date": 1655095472.42074,
      "url": "https://elbuho.bandcamp.com/album/a-guide-to-the-birds-of-south-america-ep",
      "art_id": 921079384,
      "amount_paid_fmt": "€3",
      "item_type": "a",
      "item_price": 0,
      "details": {
        "type": "album",
        "stories": [
          "",
          "",
          "",
          "",
          "",
          "",
          "",
          "",
          ""
        ]
      }
    },
    {
      "utc_date": 1653727393.10537,
      "country": "Mexico",
      "artist_name": "el cómodo silencio de los que hablan poco",
      "currency": "USD",
      "amount_paid_fmt": "$10",
      "item_description": "Amanda",
      "item_price": 0,
      "slug_type": "a",
      "amount_paid": 10,
      "art_id": 240260757,
      "url": "https://ecsdlqhp.bandcamp.com/album/amanda",
      "country_code": "mx",
      "amount_over_fmt": "$10",
      "art_url": "https://f4.bcbits.com/img/a0240260757_7.jpg",
      "item_type": "a",
      "amount_paid_usd": 10,
      "details": {
        "type": "album",
        "stories": [
          "",
          "",
          "",
          "",
          "",
          ""
        ]
      }
    },
    {
      "item_description": "BLENDS.1 - Neoperreo",
      "country": "Mexico",
      "artist_name": "El Cucuy",
      "currency": "USD",
      "amount_paid_fmt": "$1",
      "item_price": 0,
      "slug_type": "a",
      "amount_paid": 1,
      "art_id": 2525275972,
      "art_url": "https://f4.bcbits.com/img/a2525275972_7.jpg",
      "amount_paid_usd": 1,
      "url": "https://elcucuymusic.bandcamp.com/album/blends-1-neoperreo",
      "item_type": "a",
      "country_code": "mx",
      "utc_date": 1654225852.79408,
      "details": {
        "type": "album",
        "stories": [
          "",
          "",
          "",
          "",
          "",
          "",
          "",
          "",
          "",
          "",
          "",
          "",
          ""
        ]
      }
    },
    {
      "country": "United States",
      "artist_name": "El Flyin' & the Heathen Troubadours",
      "currency": "USD",
      "amount_paid_fmt": "$1",
      "item_price": 0,
      "slug_type": "a",
      "amount_paid": 1,
      "art_id": 787864886,
      "art_url": "https://f4.bcbits.com/img/a0787864886_7.jpg",
      "amount_paid_usd": 1,
      "url": "https://heathentroubadours.bandcamp.com/album/e-p",
      "item_description": "E.P.",
      "item_type": "a",
      "country_code": "us",
      "utc_date": 1654267412.63129,
      "details": {
        "type": "album",
        "stories": [
          "",
          "",
          "",
          "",
          ""
        ]
      }
    },
    {
      "country": "France",
      "artist_name": "El Gato Negro Tropical",
      "currency": "EUR",
      "amount_paid_fmt": "€2",
      "item_price": 0,
      "item_description": "Ouvre la Porte Remix Album",
      "slug_type": "a",
      "amount_paid": 2,
      "art_id": 1550366247,
      "amount_over_fmt": "€2",
      "art_url": "https://f4.bcbits.com/img/a1550366247_7.jpg",
      "amount_paid_usd": 2.14,
      "url": "https://elgatonegro.bandcamp.com/album/ouvre-la-porte-remix-album",
      "item_type": "a",
      "country_code": "fr",
      "utc_date": 1654284387.83312,
      "details": {
        "type": "album",
        "stories": [
          "",
          "",
          "",
          "",
          "",
          "",
          "",
          "",
          "",
          ""
        ]
      }
    },
    {
      "item_type": "a",
      "country_code": "us",
      "utc_date": 1654385296.55829,
      "country": "United States",
      "item_description": "Ten Songs from Quarantine",
      "artist_name": "El Greco",
      "currency": "USD",
      "amount_paid_fmt": "$1",
      "item_price": 0,
      "slug_type": "a",
      "amount_paid": 1,
      "url": "https://theelgreco.bandcamp.com/album/ten-songs-from-quarantine",
      "art_id": 2359584278,
      "art_url": "https://f4.bcbits.com/img/a2359584278_7.jpg",
      "amount_paid_usd": 1,
      "details": {
        "type": "album",
        "stories": [
          "",
          "",
          "",
          "",
          "",
          ""
        ]
      }
    },
    {
      "utc_date": 1653860631.57317,
      "country": "Hungary",
      "artist_name": "El Huervo",
      "currency": "USD",
      "amount_paid_fmt": "$1",
      "item_price": 0,
      "slug_type": "a",
      "amount_paid": 1,
      "art_id": 1497420590,
      "url": "https://elhuervo.bandcamp.com/album/a-thing-with-feathers",
      "country_code": "hu",
      "art_url": "https://f4.bcbits.com/img/a1497420590_7.jpg",
      "item_type": "a",
      "amount_paid_usd": 1,
      "item_description": "A Thing With Feathers",
      "details": {
        "type": "track",
        "stories": [
          "",
          "",
          "",
          "",
          "",
          "",
          ""
        ]
      }
    },
    {
      "country": "Japan",
      "artist_name": "El Incendio Más Largo del Mundo",
      "currency": "USD",
      "amount_paid_fmt": "$1",
      "item_price": 0,
      "slug_type": "a",
      "amount_paid": 1,
      "item_description": "Mantra Oscuro",
      "art_id": 1591286603,
      "art_url": "https://f4.bcbits.com/img/a1591286603_7.jpg",
      "amount_paid_usd": 1,
      "url": "https://incendiomaslargo.bandcamp.com/album/mantra-oscuro",
      "item_type": "a",
      "country_code": "jp",
      "utc_date": 1654236624.7454,
      "details": {
        "type": "album",
        "stories": [
          "",
          "",
          "",
          "",
          "",
          "",
          "",
          "",
          "",
          ""
        ]
      }
    },
    {
      "utc_date": 1653915477.3419,
      "country": "Mexico",
      "artist_name": "El Pseudo",
      "currency": "MXN",
      "item_description": "EL PSEUDO //> BOOTLEGS",
      "amount_paid_fmt": "$20 MXN",
      "item_price": 0,
      "slug_type": "a",
      "amount_paid": 20,
      "art_id": 2423495372,
      "url": "https://hypersonics.bandcamp.com/album/el-pseudo-bootlegs",
      "country_code": "mx",
      "art_url": "https://f4.bcbits.com/img/a2423495372_7.jpg",
      "item_type": "a",
      "amount_paid_usd": 1.03,
      "details": {
        "type": "album",
        "stories": [
          "",
          "",
          "",
          "",
          "",
          "",
          "",
          "",
          "",
          "",
          "",
          "",
          "",
          ""
        ]
      }
    },
    {
      "country": "France",
      "artist_name": "El Tigr3",
      "currency": "USD",
      "amount_paid_fmt": "$7",
      "item_price": 0,
      "slug_type": "a",
      "amount_paid": 7,
      "art_id": 1908172185,
      "amount_over_fmt": "$7",
      "art_url": "https://f4.bcbits.com/img/a1908172185_7.jpg",
      "amount_paid_usd": 7,
      "url": "https://eltigre.bandcamp.com/album/the-beast-within",
      "item_type": "a",
      "country_code": "fr",
      "item_description": "The Beast Within",
      "utc_date": 1654128197.44744,
      "details": {
        "type": "album",
        "stories": [
          "",
          "",
          "",
          "",
          "",
          "",
          "",
          ""
        ]
      }
    },
    {
      "country": "United States",
      "item_description": "Man-eater",
      "artist_name": "El Tigr3",
      "currency": "USD",
      "amount_paid_fmt": "$3",
      "item_price": 0,
      "slug_type": "a",
      "amount_paid": 3,
      "art_id": 3723038147,
      "amount_over_fmt": "$3",
      "art_url": "https://f4.bcbits.com/img/a3723038147_7.jpg",
      "amount_paid_usd": 3,
      "url": "https://eltigre.bandcamp.com/album/man-eater",
      "item_type": "a",
      "country_code": "us",
      "utc_date": 1654198404.21327,
      "details": {
        "type": "album",
        "stories": [
          "",
          "",
          "",
          "",
          "",
          "",
          "",
          ""
        ]
      }
    },
    {
      "country": "United Kingdom",
      "artist_name": "El-Ahrairah",
      "currency": "USD",
      "amount_paid_fmt": "$1",
      "item_description": "The Blessing",
      "item_price": 0,
      "slug_type": "a",
      "amount_paid": 1,
      "art_id": 3990521929,
      "art_url": "https://f4.bcbits.com/img/a3990521929_7.jpg",
      "amount_paid_usd": 1,
      "url": "https://el-ahrairah.bandcamp.com/album/the-blessing",
      "item_type": "a",
      "country_code": "gb",
      "utc_date": 1654113040.23505,
      "details": {
        "type": "album",
        "stories": [
          "",
          "",
          "",
          "",
          "",
          ""
        ]
      }
    },
    {
      "item_description": "El-Ahrairah",
      "country": "United Kingdom",
      "artist_name": "El-Ahrairah",
      "currency": "USD",
      "amount_paid_fmt": "$1",
      "item_price": 0,
      "slug_type": "a",
      "amount_paid": 1,
      "art_id": 2943145734,
      "art_url": "https://f4.bcbits.com/img/a2943145734_7.jpg",
      "amount_paid_usd": 1,
      "url": "https://el-ahrairah.bandcamp.com/album/el-ahrairah-2",
      "item_type": "a",
      "country_code": "gb",
      "utc_date": 1654127000.71882,
      "details": {
        "type": "album",
        "stories": [
          "",
          "",
          "",
          "",
          "",
          ""
        ]
      }
    },
    {
      "country": "Canada",
      "artist_name": "EL.WAV",
      "currency": "USD",
      "amount_paid_fmt": "$7.91",
      "item_price": 0,
      "slug_type": "a",
      "amount_paid": 7.91,
      "art_id": 3793990883,
      "amount_over_fmt": "$7.91",
      "art_url": "https://f4.bcbits.com/img/a3793990883_7.jpg",
      "amount_paid_usd": 7.91,
      "url": "https://elmnt.bandcamp.com/album/el-wav-flips-ii-2",
      "item_description": "EL.WAV - FLIPS II",
      "item_type": "a",
      "country_code": "ca",
      "utc_date": 1654172999.30269,
      "details": {
        "type": "album",
        "stories": [
          "",
          "",
          "",
          "",
          "",
          "",
          "",
          "",
          "",
          "",
          ""
        ]
      }
    },
    {
      "country": "United Kingdom",
      "artist_name": "Elan Noon",
      "currency": "USD",
      "amount_paid_fmt": "$1.60",
      "item_price": 0,
      "slug_type": "a",
      "amount_paid": 1.6,
      "art_id": 2244593944,
      "item_description": "Caricature",
      "art_url": "https://f4.bcbits.com/img/a2244593944_7.jpg",
      "amount_paid_usd": 1.6,
      "url": "https://elannoon.bandcamp.com/album/caricature",
      "item_type": "a",
      "country_code": "gb",
      "utc_date": 1654244311.64089,
      "details": {
        "type": "album",
        "stories": [
          "",
          "",
          "",
          "",
          "",
          "",
          "",
          "",
          "",
          "",
          ""
        ]
      }
    },
    {
      "utc_date": 1653793818.84813,
      "country": "United States",
      "artist_name": "Elder",
      "currency": "USD",
      "amount_paid_fmt": "$2",
      "item_description": "In Procession/Halcyon (Live Session)",
      "item_price": 0,
      "slug_type": "a",
      "amount_paid": 2,
      "art_id": 3004699621,
      "url": "https://beholdtheelder.bandcamp.com/album/in-procession-halcyon-live-session",
      "country_code": "us",
      "art_url": "https://f4.bcbits.com/img/a3004699621_7.jpg",
      "item_type": "a",
      "amount_paid_usd": 2,
      "details": {
        "type": "album",
        "stories": [
          "",
          "",
          "",
          ""
        ]
      }
    },
    {
      "amount_paid": 1,
      "country_code": "us",
      "art_url": "https://f4.bcbits.com/img/a3945109042_7.jpg",
      "slug_type": "a",
      "amount_paid_usd": 1,
      "country": "United States",
      "artist_name": "Elder Jack",
      "currency": "USD",
      "utc_date": 1655139851.59021,
      "url": "https://larry187.bandcamp.com/album/elder-jack-long-play",
      "art_id": 3945109042,
      "amount_paid_fmt": "$1",
      "item_type": "a",
      "item_price": 0,
      "item_description": "Elder Jack Long Play",
      "details": {
        "type": "track",
        "stories": [
          "",
          "",
          "",
          "",
          "",
          ""
        ]
      }
    },
    {
      "item_type": "a",
      "country_code": "us",
      "utc_date": 1654468134.81512,
      "country": "United States",
      "item_description": "Haunted Homecoming",
      "artist_name": "Eldritch Alabama",
      "currency": "USD",
      "amount_paid_fmt": "$5",
      "item_price": 0,
      "slug_type": "a",
      "amount_paid": 5,
      "url": "https://eldritchalabama.bandcamp.com/album/haunted-homecoming",
      "art_id": 2205865037,
      "amount_over_fmt": "$5",
      "art_url": "https://f4.bcbits.com/img/a2205865037_7.jpg",
      "amount_paid_usd": 5,
      "details": {
        "type": "album",
        "stories": [
          "",
          "",
          "",
          "",
          "",
          "",
          "",
          "",
          "",
          "",
          "",
          "",
          "",
          "",
          ""
        ]
      }
    },
    {
      "item_type": "a",
      "country_code": "us",
      "utc_date": 1654356041.79181,
      "country": "United States",
      "artist_name": "Eleanor Two",
      "currency": "USD",
      "amount_paid_fmt": "$5",
      "item_price": 0,
      "slug_type": "a",
      "amount_paid": 5,
      "url": "https://eleanortwo.bandcamp.com/album/future-passages-demos",
      "item_description": "Future Passages Demos",
      "art_id": 2385060384,
      "amount_over_fmt": "$5",
      "art_url": "https://f4.bcbits.com/img/a2385060384_7.jpg",
      "amount_paid_usd": 5,
      "details": {
        "type": "album",
        "stories": [
          "",
          "",
          "",
          "",
          "",
          "",
          "",
          ""
        ]
      }
    },
    {
      "utc_date": 1653790479.33433,
      "country": "United States",
      "item_description": "Live At The House Of Blues-NOLA",
      "artist_name": "Electric Age",
      "currency": "USD",
      "amount_paid_fmt": "$5",
      "item_price": 0,
      "slug_type": "a",
      "amount_paid": 5,
      "art_id": 1280991288,
      "url": "https://electricagela.bandcamp.com/album/live-at-the-house-of-blues-nola",
      "country_code": "us",
      "amount_over_fmt": "$5",
      "art_url": "https://f4.bcbits.com/img/a1280991288_7.jpg",
      "item_type": "a",
      "amount_paid_usd": 5,
      "details": {
        "type": "album",
        "stories": [
          "",
          "",
          "",
          "",
          "",
          "",
          ""
        ]
      }
    },
    {
      "amount_paid": 1,
      "country_code": "us",
      "art_url": "https://f4.bcbits.com/img/a0249606826_7.jpg",
      "item_description": "saxofonia II",
      "slug_type": "a",
      "amount_paid_usd": 1,
      "country": "United States",
      "artist_name": "Electric Citizen",
      "currency": "USD",
      "utc_date": 1655166989.47839,
      "url": "https://electriccitizen.bandcamp.com/album/saxofonia-ii",
      "art_id": 249606826,
      "amount_paid_fmt": "$1",
      "item_type": "a",
      "item_price": 0,
      "details": {
        "type": "track",
        "stories": [
          "",
          "",
          "",
          "",
          "",
          "",
          ""
        ]
      }
    },
    {
      "country": "Belgium",
      "item_description": "e c o s p h e r e",
      "artist_name": "Electric Dreams",
      "currency": "USD",
      "amount_paid_fmt": "$1",
      "item_price": 0,
      "slug_type": "a",
      "amount_paid": 1,
      "art_id": 1122289830,
      "art_url": "https://f4.bcbits.com/img/a1122289830_7.jpg",
      "amount_paid_usd": 1,
      "url": "https://geometriclullaby.bandcamp.com/album/e-c-o-s-p-h-e-r-e",
      "item_type": "a",
      "country_code": "be",
      "utc_date": 1654288012.33463,
      "details": {
        "type": "track",
        "stories": [
          "",
          "",
          "",
          "",
          "",
          "",
          "",
          "",
          "",
          "",
          "",
          "",
          "",
          ""
        ]
      }
    },
    {
      "utc_date": 1653701463.0204,
      "country": "United States",
      "artist_name": "Electric Mountain",
      "currency": "USD",
      "amount_paid_fmt": "$7",
      "item_price": 0,
      "item_description": "Electric Mountain",
      "slug_type": "a",
      "amount_paid": 7,
      "art_id": 520214886,
      "url": "https://electricmountainband.bandcamp.com/album/electric-mountain",
      "country_code": "us",
      "amount_over_fmt": "$7",
      "art_url": "https://f4.bcbits.com/img/a0520214886_7.jpg",
      "item_type": "a",
      "amount_paid_usd": 7,
      "details": {
        "type": "track",
        "stories": [
          "",
          "",
          "",
          "",
          ""
        ]
      }
    },
    {
      "amount_paid": 9.6,
      "country_code": "us",
      "art_url": "https://f4.bcbits.com/img/a3110150478_7.jpg",
      "slug_type": "a",
      "amount_over_fmt": "€9.60",
      "amount_paid_usd": 9.99,
      "country": "United States",
      "artist_name": "electric mud",
      "currency": "EUR",
      "utc_date": 1655165018.76965,
      "url": "https://electricmud.bandcamp.com/album/lost-places",
      "item_description": "Lost Places",
      "art_id": 3110150478,
      "amount_paid_fmt": "€9.60",
      "item_type": "a",
      "item_price": 0,
      "details": {
        "type": "track",
        "stories": [
          "",
          "",
          "",
          "",
          "",
          "",
          ""
        ]
      }
    },
    {
      "utc_date": 1653889840.76772,
      "country": "United States",
      "artist_name": "Electric Needle Room",
      "currency": "USD",
      "amount_paid_fmt": "$6",
      "item_price": 0,
      "slug_type": "a",
      "item_description": "The Presidents of the United States of America (Volume 1)",
      "amount_paid": 6,
      "art_id": 569431036,
      "url": "https://electricneedleroom.bandcamp.com/album/the-presidents-of-the-united-states-of-america-volume-1",
      "country_code": "us",
      "amount_over_fmt": "$6",
      "art_url": "https://f4.bcbits.com/img/a0569431036_7.jpg",
      "item_type": "a",
      "amount_paid_usd": 6,
      "details": {
        "type": "track",
        "stories": [
          "",
          "",
          "",
          "",
          "",
          "",
          "",
          "",
          "",
          "",
          "",
          "",
          "",
          ""
        ]
      }
    },
    {
      "utc_date": 1653802573.31684,
      "country": "United States",
      "artist_name": "Electric Octopus",
      "currency": "GBP",
      "amount_paid_fmt": "£0.79",
      "item_price": 0,
      "slug_type": "a",
      "amount_paid": 0.79,
      "art_id": 476745015,
      "url": "https://electricoctopusofficial.bandcamp.com/album/this-is-our-culture",
      "country_code": "us",
      "art_url": "https://f4.bcbits.com/img/a0476745015_7.jpg",
      "item_type": "a",
      "amount_paid_usd": 1,
      "item_description": "This Is Our Culture",
      "details": {
        "type": "album",
        "stories": [
          "",
          "",
          "",
          "",
          "",
          "",
          "",
          "",
          "",
          ""
        ]
      }
    },
    {
      "country": "United States",
      "artist_name": "Electric Octopus",
      "currency": "GBP",
      "amount_paid_fmt": "£1",
      "item_price": 0,
      "slug_type": "a",
      "amount_paid": 1,
      "item_description": "Driving Under The Influence Of Jams",
      "art_id": 3201110788,
      "art_url": "https://f4.bcbits.com/img/a3201110788_7.jpg",
      "amount_paid_usd": 1.26,
      "url": "https://electricoctopusofficial.bandcamp.com/album/driving-under-the-influence-of-jams",
      "item_type": "a",
      "country_code": "us",
      "utc_date": 1654200593.79365,
      "details": {
        "type": "album",
        "stories": [
          "",
          "",
          "",
          "",
          "",
          "",
          ""
        ]
      }
    },
    {
      "country": "Australia",
      "artist_name": "Electric Octopus",
      "currency": "GBP",
      "amount_paid_fmt": "£7",
      "item_description": "St. Patrick's Cough",
      "item_price": 0,
      "slug_type": "a",
      "amount_paid": 7,
      "art_id": 2820796592,
      "amount_over_fmt": "£7",
      "art_url": "https://f4.bcbits.com/img/a2820796592_7.jpg",
      "amount_paid_usd": 8.8,
      "url": "https://electricoctopusofficial.bandcamp.com/album/st-patricks-cough",
      "item_type": "a",
      "country_code": "au",
      "utc_date": 1654240655.96591,
      "details": {
        "type": "track",
        "stories": [
          "",
          "",
          "",
          "",
          "",
          "",
          ""
        ]
      }
    },
    {
      "item_type": "a",
      "country_code": "sg",
      "utc_date": 1654315561.99779,
      "country": "Singapore",
      "artist_name": "Electric Octopus",
      "currency": "GBP",
      "amount_paid_fmt": "£9",
      "item_price": 0,
      "slug_type": "a",
      "item_description": "Inclinations",
      "amount_paid": 9,
      "url": "https://electricoctopusofficial.bandcamp.com/album/inclinations",
      "art_id": 273476482,
      "amount_over_fmt": "£9",
      "art_url": "https://f4.bcbits.com/img/a0273476482_7.jpg",
      "amount_paid_usd": 11.24,
      "details": {
        "type": "album",
        "stories": [
          "",
          "",
          "",
          "",
          "",
          "",
          "",
          "",
          "",
          "",
          ""
        ]
      }
    },
    {
      "item_type": "a",
      "country_code": "ua",
      "utc_date": 1654361457.6536,
      "country": "Ukraine",
      "artist_name": "Electric Octopus",
      "currency": "GBP",
      "amount_paid_fmt": "£1",
      "item_description": "Smokyhead",
      "item_price": 0,
      "slug_type": "a",
      "amount_paid": 1,
      "url": "https://electricoctopusofficial.bandcamp.com/album/smokyhead",
      "art_id": 2445370429,
      "art_url": "https://f4.bcbits.com/img/a2445370429_7.jpg",
      "amount_paid_usd": 1.25,
      "details": {
        "type": "album",
        "stories": [
          "",
          "",
          "",
          "",
          "",
          "",
          ""
        ]
      }
    },
    {
      "amount_paid": 7,
      "country_code": "us",
      "art_url": "https://f4.bcbits.com/img/a1351827988_7.jpg",
      "slug_type": "a",
      "amount_over_fmt": "£7",
      "amount_paid_usd": 8.46,
      "country": "United States",
      "artist_name": "Electric Octopus",
      "currency": "GBP",
      "utc_date": 1655209885.29342,
      "url": "https://electricoctopusofficial.bandcamp.com/album/live-at-klub-kocka",
      "item_description": "Live At Klub Kocka",
      "art_id": 1351827988,
      "amount_paid_fmt": "£7",
      "item_type": "a",
      "item_price": 0,
      "details": {
        "type": "album",
        "stories": [
          "",
          "",
          "",
          "",
          "",
          "",
          "",
          "",
          "",
          "",
          "",
          ""
        ]
      }
    },
    {
      "item_type": "a",
      "country_code": "us",
      "utc_date": 1654375233.69543,
      "item_description": "MOTHER IRON HORSE - THE LESSER KEY",
      "country": "United States",
      "artist_name": "Electric Valley Records",
      "currency": "EUR",
      "amount_paid_fmt": "€1",
      "item_price": 0,
      "slug_type": "a",
      "amount_paid": 1,
      "url": "https://evrecords.bandcamp.com/album/mother-iron-horse-the-lesser-key",
      "art_id": 1404345606,
      "art_url": "https://f4.bcbits.com/img/a1404345606_7.jpg",
      "amount_paid_usd": 1.07,
      "details": {
        "type": "track",
        "stories": [
          "",
          "",
          "",
          "",
          "",
          "",
          ""
        ]
      }
    },
    {
      "item_type": "a",
      "country_code": "us",
      "utc_date": 1654431897.46761,
      "item_description": "Arteaga / Atomic Mold Split Album",
      "country": "United States",
      "artist_name": "Electric Valley Records",
      "currency": "EUR",
      "amount_paid_fmt": "€6",
      "item_price": 0,
      "slug_type": "a",
      "amount_paid": 6,
      "url": "https://evrecords.bandcamp.com/album/arteaga-atomic-mold-split-album",
      "art_id": 2291368774,
      "amount_over_fmt": "€6",
      "art_url": "https://f4.bcbits.com/img/a2291368774_7.jpg",
      "amount_paid_usd": 6.43,
      "details": {
        "type": "track",
        "stories": [
          "",
          "",
          "",
          "",
          "",
          "",
          ""
        ]
      }
    },
    {
      "country": "United States",
      "artist_name": "Electric Voice Records",
      "currency": "CAD",
      "amount_paid_fmt": "$1 CAD",
      "item_price": 0,
      "slug_type": "a",
      "item_description": "Cliff Dwellings.",
      "amount_paid": 1,
      "art_id": 1526367841,
      "art_url": "https://f4.bcbits.com/img/a1526367841_7.jpg",
      "amount_paid_usd": 0.8,
      "url": "https://electricvoicerecords.bandcamp.com/album/cliff-dwellings",
      "item_type": "a",
      "country_code": "us",
      "utc_date": 1654210573.18348,
      "details": {
        "type": "album",
        "stories": [
          "",
          ""
        ]
      }
    },
    {
      "country": "United States",
      "item_description": "Sand Beach.",
      "artist_name": "Electric Voice Records",
      "currency": "CAD",
      "amount_paid_fmt": "$1 CAD",
      "item_price": 0,
      "slug_type": "a",
      "amount_paid": 1,
      "art_id": 1805644151,
      "art_url": "https://f4.bcbits.com/img/a1805644151_7.jpg",
      "amount_paid_usd": 0.8,
      "url": "https://electricvoicerecords.bandcamp.com/album/sand-beach",
      "item_type": "a",
      "country_code": "us",
      "utc_date": 1654210642.23641,
      "details": {
        "type": "album",
        "stories": [
          "",
          ""
        ]
      }
    },
    {
      "item_description": "Electric Voice II (LP, 2013)",
      "item_type": "a",
      "country_code": "us",
      "utc_date": 1654315024.10164,
      "country": "United States",
      "artist_name": "Electric Voice Records",
      "currency": "CAD",
      "amount_paid_fmt": "$1 CAD",
      "item_price": 0,
      "slug_type": "a",
      "amount_paid": 1,
      "url": "https://electricvoicerecords.bandcamp.com/album/electric-voice-ii-lp-2013",
      "art_id": 46738318,
      "art_url": "https://f4.bcbits.com/img/a0046738318_7.jpg",
      "amount_paid_usd": 0.79,
      "details": {
        "type": "album",
        "stories": [
          "",
          "",
          "",
          "",
          "",
          "",
          "",
          "",
          "",
          "",
          "",
          ""
        ]
      }
    },
    {
      "country": "United States",
      "artist_name": "Electric Yawn",
      "currency": "AUD",
      "amount_paid_fmt": "$1 AUD",
      "item_price": 0,
      "slug_type": "a",
      "amount_paid": 1,
      "art_id": 3236408401,
      "art_url": "https://f4.bcbits.com/img/a3236408401_7.jpg",
      "item_description": "Dopamine Farm",
      "amount_paid_usd": 0.72,
      "url": "https://electricyawn.bandcamp.com/album/dopamine-farm",
      "item_type": "a",
      "country_code": "us",
      "utc_date": 1654128931.09772,
      "details": {
        "type": "album",
        "stories": [
          "",
          "",
          "",
          "",
          "",
          "",
          "",
          "",
          "",
          "",
          "",
          "",
          ""
        ]
      }
    },
    {
      "country": "Portugal",
      "artist_name": "Electricmoon Records",
      "currency": "EUR",
      "amount_paid_fmt": "€0.60",
      "item_price": 0,
      "slug_type": "a",
      "amount_paid": 0.6,
      "art_id": 2939332996,
      "art_url": "https://f4.bcbits.com/img/a2939332996_7.jpg",
      "amount_paid_usd": 0.64,
      "url": "https://electricmoonrecords.bandcamp.com/album/va-synapses-renovation-2",
      "item_description": "VA - Synapses Renovation 2",
      "item_type": "a",
      "country_code": "pt",
      "utc_date": 1654162456.48592,
      "details": {
        "type": "track",
        "stories": [
          "",
          "",
          "",
          "",
          "",
          "",
          ""
        ]
      }
    },
    {
      "country": "Denmark",
      "artist_name": "Electricmoon Records",
      "currency": "EUR",
      "amount_paid_fmt": "€5",
      "item_price": 0,
      "slug_type": "a",
      "amount_paid": 5,
      "art_id": 614166332,
      "amount_over_fmt": "€5",
      "art_url": "https://f4.bcbits.com/img/a0614166332_7.jpg",
      "amount_paid_usd": 5.35,
      "url": "https://electricmoonrecords.bandcamp.com/album/va-binary-code",
      "item_type": "a",
      "country_code": "dk",
      "item_description": "VA - Binary Code",
      "utc_date": 1654173001.43976,
      "details": {
        "type": "track",
        "stories": [
          "",
          "",
          "",
          "",
          "",
          "",
          "",
          "",
          ""
        ]
      }
    },
    {
      "item_type": "a",
      "country_code": "au",
      "utc_date": 1654348974.705,
      "item_description": "The Hass Effect",
      "country": "Australia",
      "artist_name": "Electrocado",
      "currency": "USD",
      "amount_paid_fmt": "$10",
      "item_price": 0,
      "slug_type": "a",
      "amount_paid": 10,
      "url": "https://electrocado.bandcamp.com/album/the-hass-effect",
      "art_id": 3520803809,
      "amount_over_fmt": "$10",
      "art_url": "https://f4.bcbits.com/img/a3520803809_7.jpg",
      "amount_paid_usd": 10,
      "details": {
        "type": "album",
        "stories": [
          "",
          "",
          "",
          "",
          "",
          "",
          "",
          "",
          "",
          "",
          "",
          "",
          "",
          "",
          "",
          ""
        ]
      }
    },
    {
      "item_type": "a",
      "country_code": "us",
      "utc_date": 1654320498.12169,
      "country": "United States",
      "artist_name": "Electromagnetic Blaze",
      "currency": "USD",
      "amount_paid_fmt": "$1",
      "item_price": 0,
      "slug_type": "a",
      "item_description": "Electromagnetism EP",
      "amount_paid": 1,
      "url": "https://electromagneticblaze.bandcamp.com/album/electromagnetism-ep",
      "art_id": 318231566,
      "art_url": "https://f4.bcbits.com/img/a0318231566_7.jpg",
      "amount_paid_usd": 1,
      "details": {
        "type": "album",
        "stories": [
          "",
          "",
          "",
          "",
          "",
          ""
        ]
      }
    },
    {
      "item_description": "Your Future Awaits",
      "utc_date": 1653729740.32433,
      "country": "United Kingdom",
      "artist_name": "Electron Odyssey",
      "currency": "USD",
      "amount_paid_fmt": "$6",
      "item_price": 0,
      "slug_type": "a",
      "amount_paid": 6,
      "art_id": 680340366,
      "url": "https://electronodyssey.bandcamp.com/album/your-future-awaits",
      "country_code": "gb",
      "amount_over_fmt": "$6",
      "art_url": "https://f4.bcbits.com/img/a0680340366_7.jpg",
      "item_type": "a",
      "amount_paid_usd": 6,
      "details": {
        "type": "track",
        "stories": [
          "",
          "",
          "",
          "",
          "",
          "",
          "",
          "",
          "",
          "",
          "",
          "",
          ""
        ]
      }
    }
  ],
  "first": "ECHELON (International)",
  "last": "Electron Odyssey",
  "after": [
    "electronique",
    {
      "@ref": {
        "id": "332869132481462466",
        "collection": {
          "@ref": {
            "id": "scrapes",
            "collection": {
              "@ref": {
                "id": "collections"
              }
            }
          }
        }
      }
    },
    {
      "@ref": {
        "id": "332869132481462466",
        "collection": {
          "@ref": {
            "id": "scrapes",
            "collection": {
              "@ref": {
                "id": "collections"
              }
            }
          }
        }
      }
    }
  ],
  "before": [
    "ECHELON (International)",
    {
      "@ref": {
        "id": "333307135930663106",
        "collection": {
          "@ref": {
            "id": "scrapes",
            "collection": {
              "@ref": {
                "id": "collections"
              }
            }
          }
        }
      }
    },
    {
      "@ref": {
        "id": "333307135930663106",
        "collection": {
          "@ref": {
            "id": "scrapes",
            "collection": {
              "@ref": {
                "id": "collections"
              }
            }
          }
        }
      }
    }
  ]
}